cudara_client/__init__.py
cudara_client/py.typed
cudara_client-0.0.1.dist-info/METADATA
cudara_client-0.0.1.dist-info/WHEEL
cudara_client-0.0.1.dist-info/entry_points.txt
cudara_client-0.0.1.dist-info/licenses/LICENSE
cudara_client-0.0.1.dist-info/RECORD
