Metadata-Version: 2.4
Name: cudara-client
Version: 0.0.1
Summary: Python client for Cudara inference server with prompt engineering utilities
Project-URL: Homepage, https://github.com/juliog922/cudara
Project-URL: Repository, https://github.com/juliog922/cudara
Project-URL: Documentation, https://github.com/juliog922/cudara#cudara-client
Project-URL: Issues, https://github.com/juliog922/cudara/issues
Project-URL: Changelog, https://github.com/juliog922/cudara/blob/main/CHANGELOG.md
Author: Julio Galindo
License: MIT
License-File: LICENSE
Keywords: ai,client,cudara,embeddings,inference,llm,ollama,vlm
Classifier: Development Status :: 4 - Beta
Classifier: Intended Audience :: Developers
Classifier: License :: OSI Approved :: MIT License
Classifier: Operating System :: OS Independent
Classifier: Programming Language :: Python :: 3
Classifier: Programming Language :: Python :: 3.12
Classifier: Programming Language :: Python :: 3.13
Classifier: Topic :: Scientific/Engineering :: Artificial Intelligence
Classifier: Topic :: Software Development :: Libraries :: Python Modules
Classifier: Typing :: Typed
Requires-Python: >=3.12
Requires-Dist: httpx>=0.28.1
Provides-Extra: dev
Requires-Dist: mypy>=1.8.0; extra == 'dev'
Requires-Dist: pytest-asyncio>=0.23.0; extra == 'dev'
Requires-Dist: pytest-httpx>=0.30.0; extra == 'dev'
Requires-Dist: pytest>=8.0.0; extra == 'dev'
Requires-Dist: ruff>=0.14.9; extra == 'dev'
